flybook/__init__.py
flybook/common.py
flybook/customBot.py
flybook/user.py
flybook/bitable/__init__.py
flybook/bitable/bitable.py
flybook/bitable/filter.py
flybook/bitable/table.py
flybook/bot/__init__.py
flybook/bot/downloader.py
flybook/bot/messageRelier.py
flybook/bot/messageSender.py
flybook/bot/prototype.py
flybook/listener/__init__.py
flybook/message/__init__.py
flybook/message/card.py
flybook/message/markdown.py
flybook/message/prototype.py
flybook/message/text.py
flybook-0.5.3.dist-info/licenses/LICENSE
test/listener.py
test/test_bitable.py
test/test_bot.py
test/test_customBot.py
test/test_filter.py
flybook-0.5.3.dist-info/METADATA
flybook-0.5.3.dist-info/WHEEL
flybook-0.5.3.dist-info/top_level.txt
flybook-0.5.3.dist-info/RECORD
